structlog_wrap.py
structlog_wrap-1.0.0.dist-info/licenses/LICENSE
structlog_wrap-1.0.0.dist-info/METADATA
structlog_wrap-1.0.0.dist-info/WHEEL
structlog_wrap-1.0.0.dist-info/top_level.txt
structlog_wrap-1.0.0.dist-info/RECORD
