Metadata-Version: 2.4
Name: structlog-wrap
Version: 1.0.0
Summary: 基于structlog的函数日志装饰器，自动打印函数调用日志 - A structlog-based function logging decorator that automatically prints function call logs
Home-page: https://github.com/yourusername/structlog-wrap
Author: Your Name
Author-email: structlog-wrap <structlog.wrap@example.com>
Maintainer-email: structlog-wrap <structlog.wrap@example.com>
License: MIT
Project-URL: Homepage, https://pypi.org/project/structlog-wrap/
Project-URL: Repository, https://github.com/structlog-wrap/structlog-wrap
Project-URL: Issues, https://github.com/structlog-wrap/structlog-wrap/issues
Project-URL: Documentation, https://github.com/structlog-wrap/structlog-wrap#readme
Keywords: structlog,logging,decorator,function,calls
Classifier: Development Status :: 5 - Production/Stable
Classifier: Intended Audience :: Developers
Classifier: License :: OSI Approved :: MIT License
Classifier: Operating System :: OS Independent
Classifier: Programming Language :: Python :: 3
Classifier: Programming Language :: Python :: 3.8
Classifier: Programming Language :: Python :: 3.9
Classifier: Programming Language :: Python :: 3.10
Classifier: Programming Language :: Python :: 3.11
Classifier: Programming Language :: Python :: 3.12
Classifier: Topic :: Software Development :: Libraries :: Python Modules
Classifier: Topic :: System :: Logging
Classifier: Topic :: Utilities
Requires-Python: >=3.8
License-File: LICENSE
Requires-Dist: structlog>=23.1.0
Requires-Dist: colorama>=0.4.6
Provides-Extra: dev
Requires-Dist: pytest>=6.0; extra == "dev"
Requires-Dist: pytest-cov; extra == "dev"
Requires-Dist: black; extra == "dev"
Requires-Dist: flake8; extra == "dev"
Dynamic: author
Dynamic: home-page
Dynamic: license-file
Dynamic: requires-python
